nanopub_sign-0.1.10.dist-info/METADATA
nanopub_sign-0.1.10.dist-info/WHEEL
nanopub_sign-0.1.10.dist-info/license_files/LICENSE.txt
nanopub_sign/__init__.py
nanopub_sign/nanopub_sign.pypy311-pp73-darwin.so
nanopub_sign-0.1.10.dist-info/RECORD
