Metadata-Version: 2.1
Name: nanopub-sign
Version: 0.1.10
Classifier: Development Status :: 4 - Beta
Classifier: Intended Audience :: Developers
Classifier: License :: OSI Approved :: MIT License
Classifier: Programming Language :: Python :: 3 :: Only
Classifier: Programming Language :: Python :: 3.8
Classifier: Programming Language :: Python :: 3.9
Classifier: Programming Language :: Python :: 3.10
Classifier: Programming Language :: Python :: 3.11
Classifier: Programming Language :: Python :: 3.12
Classifier: Programming Language :: Rust
Classifier: Topic :: Software Development :: Libraries :: Python Modules
License-File: LICENSE.txt
Summary: Python bindings for the Nanopub rust toolkit
Keywords: nanopublications,rdf,linked-data,semantic-web
Home-Page: https://vemonet.github.io/nanopub-rs
Author: Vincent Emonet <vincent.emonet@gmail.com>
Author-email: Vincent Emonet <vincent.emonet@gmail.com>
Requires-Python: >=3.8, <3.13
Project-URL: Changelog, https://github.com/vemonet/nanopub-rs/blob/main/CHANGELOG.md
Project-URL: Documentation, https://vemonet.github.io/nanopub-rs
Project-URL: Homepage, https://vemonet.github.io/nanopub-rs
Project-URL: Source, https://github.com/vemonet/nanopub-rs/tree/main/python
Project-URL: Tracker, https://github.com/vemonet/nanopub-rs/issues
